{
  "behaviorResults": [
    {
      "name": "home_autoplay_pause_resume_drag_viewport",
      "passed": true
    },
    {
      "name": "brand_filter_reorganizes_and_browser_back_restores",
      "passed": true
    },
    {
      "name": "product_gallery_accepts_natural_swipe",
      "passed": true
    },
    {
      "name": "reduced_motion_disables_autoplay_but_keeps_manual_navigation",
      "passed": true
    }
  ],
  "consoleErrors": [],
  "directSupabaseRequests": [],
  "failedResponses": [],
  "pageErrors": [],
  "screenshots": [
    "catalog-brand-filter-390x844.png",
    "catalog-home-preview-1440x900.png",
    "catalog-home-preview-390x844.png",
    "catalog-index-1440x900.png",
    "catalog-index-390x844.png",
    "catalog-product-1440x900.png",
    "catalog-product-390x844.png"
  ],
  "videos": [
    "catalog-interactions.webm",
    "catalog-reduced-motion.webm"
  ],
  "viewportResults": [
    {
      "height": 900,
      "passed": true,
      "width": 1440,
      "worstLayoutShift": 0
    },
    {
      "height": 768,
      "passed": true,
      "width": 1366,
      "worstLayoutShift": 0
    },
    {
      "height": 800,
      "passed": true,
      "width": 360,
      "worstLayoutShift": 0
    },
    {
      "height": 812,
      "passed": true,
      "width": 375,
      "worstLayoutShift": 0
    },
    {
      "height": 844,
      "passed": true,
      "width": 390,
      "worstLayoutShift": 0
    },
    {
      "height": 915,
      "passed": true,
      "width": 412,
      "worstLayoutShift": 0
    },
    {
      "height": 932,
      "passed": true,
      "width": 430,
      "worstLayoutShift": 0
    },
    {
      "height": 1024,
      "passed": true,
      "width": 768,
      "worstLayoutShift": 0
    }
  ]
}
